module_manager/__init__.py
module_manager/main.py
module_manager-0.0.4.dist-info/METADATA
module_manager-0.0.4.dist-info/WHEEL
module_manager-0.0.4.dist-info/top_level.txt
module_manager-0.0.4.dist-info/RECORD
