Metadata-Version: 2.1
Name: module-manager
Version: 0.0.4
Summary: A Module for managing modules
Home-page: UNKNOWN
Author: darkboi3301(Eeshwar Sivasankar)
Author-email: <elite.gfx.yt@gmail.com>
License: UNKNOWN
Project-URL: github, https://github.com/darkbi3301
Project-URL: instagram, https://instagram.com/darkboi3301
Keywords: python,module,management
Platform: UNKNOWN
Classifier: Development Status :: 1 - Planning
Classifier: Intended Audience :: Developers
Classifier: Programming Language :: Python :: 3
Classifier: Operating System :: Unix
Classifier: Operating System :: MacOS :: MacOS X
Classifier: Operating System :: Microsoft :: Windows
Classifier: Programming Language :: Python :: 3
Classifier: Programming Language :: Python :: 3.6
Classifier: Programming Language :: Python :: 3.7
Classifier: Programming Language :: Python :: 3.8
Classifier: Programming Language :: Python :: 3.9
Classifier: Programming Language :: Python :: 3.10
Classifier: Programming Language :: Python :: 3 :: Only
Requires-Dist: pip
